stew/__init__.py
stew/stew.py
stew/types.py
stew-0.1.5.dist-info/WHEEL
stew-0.1.5.dist-info/METADATA
stew-0.1.5.dist-info/RECORD
