Metadata-Version: 2.1
Name: stew
Version: 0.1.5
Summary: A library for parsing localization string files
Author: Timofey Danshin
Author-email: t.danshin@gmail.com
Requires-Python: >=3.6,<4.0
Classifier: Programming Language :: Python :: 3
Classifier: Programming Language :: Python :: 3.6
Classifier: Programming Language :: Python :: 3.7
Classifier: Programming Language :: Python :: 3.8
